Metadata-Version: 2.1
Name: my_libr
Version: 0.1.0
Summary: Super useful library
Author: Petr Gregor (SDA)
License: Open-source
